unifisa_core/email/email_manager.py
unifisa_core/log/logger_config.py
unifisa_core/selenium/chrome_driver_settings.py
unifisa_core/selenium/selenium_helper.py
unifisa_core/sqlserver/sql_server_pyodbc.py
unifisa_core-0.1.0.dist-info/LICENSE
unifisa_core-0.1.0.dist-info/METADATA
unifisa_core-0.1.0.dist-info/WHEEL
unifisa_core-0.1.0.dist-info/RECORD
