Metadata-Version: 2.3
Name: unifisa_core
Version: 0.1.0
Summary: Unifisa core utilities for automation, email, logging, selenium, and SQL Server integration.
License: MIT
Keywords: unifisa,automation,selenium,email,sqlserver
Author: Jpzinn654
Author-email: juan654.pablo@gmail.com
Requires-Python: >=3.11,<4.0
Classifier: License :: OSI Approved :: MIT License
Classifier: Operating System :: OS Independent
Classifier: Programming Language :: Python :: 3
Classifier: Programming Language :: Python :: 3.11
Classifier: Programming Language :: Python :: 3.12
Classifier: Programming Language :: Python :: 3.13
Requires-Dist: loguru (>=0.7.3,<0.8.0)
Requires-Dist: pandas (>=2.3.3,<3.0.0)
Requires-Dist: pyodbc (>=5.2.0,<6.0.0)
Requires-Dist: selenium (>=4.36.0,<5.0.0)
